python_exiv2-0.10.0.dist-info/RECORD
python_exiv2-0.10.0.dist-info/LICENSE
python_exiv2-0.10.0.dist-info/WHEEL
python_exiv2-0.10.0.dist-info/top_level.txt
python_exiv2-0.10.0.dist-info/METADATA
exiv2/_error.cpython-310-darwin.so
exiv2/tags.py
exiv2/preview.py
exiv2/iptc.py
exiv2/_datasets.cpython-310-darwin.so
exiv2/_preview.cpython-310-darwin.so
exiv2/version.py
exiv2/error.py
exiv2/_basicio.cpython-310-darwin.so
exiv2/_easyaccess.cpython-310-darwin.so
exiv2/_version.cpython-310-darwin.so
exiv2/properties.py
exiv2/basicio.py
exiv2/_metadatum.cpython-310-darwin.so
exiv2/datasets.py
exiv2/__init__.py
exiv2/types.py
exiv2/xmp.py
exiv2/_value.cpython-310-darwin.so
exiv2/_iptc.cpython-310-darwin.so
exiv2/_exif.cpython-310-darwin.so
exiv2/easyaccess.py
exiv2/exif.py
exiv2/_types.cpython-310-darwin.so
exiv2/value.py
exiv2/_properties.cpython-310-darwin.so
exiv2/_image.cpython-310-darwin.so
exiv2/metadatum.py
exiv2/image.py
exiv2/__main__.py
exiv2/_tags.cpython-310-darwin.so
exiv2/_xmp.cpython-310-darwin.so
exiv2/locale/sk/LC_MESSAGES/exiv2.mo
exiv2/locale/ug/LC_MESSAGES/exiv2.mo
exiv2/locale/pl/LC_MESSAGES/exiv2.mo
exiv2/locale/vi/LC_MESSAGES/exiv2.mo
exiv2/locale/sv/LC_MESSAGES/exiv2.mo
exiv2/locale/ms/LC_MESSAGES/exiv2.mo
exiv2/locale/ca/LC_MESSAGES/exiv2.mo
exiv2/locale/ru/LC_MESSAGES/exiv2.mo
exiv2/locale/pt/LC_MESSAGES/exiv2.mo
exiv2/locale/uk/LC_MESSAGES/exiv2.mo
exiv2/locale/bs/LC_MESSAGES/exiv2.mo
exiv2/locale/gl/LC_MESSAGES/exiv2.mo
exiv2/locale/nl/LC_MESSAGES/exiv2.mo
exiv2/locale/de/LC_MESSAGES/exiv2.mo
exiv2/locale/fi/LC_MESSAGES/exiv2.mo
exiv2/locale/fr/LC_MESSAGES/exiv2.mo
exiv2/locale/es/LC_MESSAGES/exiv2.mo
exiv2/.dylibs/libintl.8.dylib
exiv2/examples/addmoddel.py
exiv2/examples/values.py
exiv2/examples/thumbnail.py
exiv2/examples/xmpsample.py
exiv2/examples/easyaccess.py
exiv2/examples/exifprint.py
exiv2/examples/exifdata.py
exiv2/examples/exifvalue.py
exiv2/examples/exifcomment.py
exiv2/examples/README.rst
exiv2/examples/iptceasy.py
exiv2/lib/libexiv2.27.dylib
