Metadata-Version: 2.1
Name: python-exiv2
Version: 0.10.0
Summary: Python interface to libexiv2
Home-page: https://github.com/jim-easterbrook/python-exiv2
Author: Jim Easterbrook
Author-email: jim@jim-easterbrook.me.uk
License: GNU GPL
Platform: POSIX
Platform: MacOS
Platform: Windows
Classifier: Development Status :: 4 - Beta
Classifier: Intended Audience :: Developers
Classifier: License :: OSI Approved :: GNU General Public License v3 or later (GPLv3+)
Classifier: Operating System :: MacOS
Classifier: Operating System :: MacOS :: MacOS X
Classifier: Operating System :: POSIX
Classifier: Operating System :: POSIX :: Linux
Classifier: Operating System :: Microsoft
Classifier: Operating System :: Microsoft :: Windows
Classifier: Programming Language :: Python :: 3
Classifier: Topic :: Multimedia
Classifier: Topic :: Multimedia :: Graphics
